pylimo/__init__.py
pylimo/limo.py
pylimo/limomsg.py
pylimo-0.3.5.dist-info/LICENSE.txt
pylimo-0.3.5.dist-info/METADATA
pylimo-0.3.5.dist-info/WHEEL
pylimo-0.3.5.dist-info/top_level.txt
pylimo-0.3.5.dist-info/RECORD
