Metadata-Version: 2.1
Name: pylimo
Version: 0.3.5
Summary: A small example package for limo
Home-page: https://github.com/agilexrobotics/limo_ros
Author: agilexrobotics
Author-email: support@agilex.ai
License: UNKNOWN
Project-URL: Bug Tracker, https://github.com/agilexrobotics/limo_ros/issues
Platform: UNKNOWN
Classifier: Programming Language :: Python :: 3.6
Classifier: Programming Language :: Python :: 3.7
Classifier: Programming Language :: Python :: 3.8
Classifier: Programming Language :: Python :: 3.9
Classifier: License :: OSI Approved :: MIT License
Requires-Python: >=3.6
License-File: LICENSE.txt
